yaml_to_markdown/__init__.py
yaml_to_markdown/convert.py
yaml_to_markdown/convert_test.py
yaml_to_markdown/md_converter.py
yaml_to_markdown/md_converter_test.py
yaml_to_markdown/utils.py
yaml_to_markdown/utils_test.py
yaml_to_markdown-0.1.1744598339.dist-info/licenses/LICENSE
yaml_to_markdown-0.1.1744598339.dist-info/METADATA
yaml_to_markdown-0.1.1744598339.dist-info/WHEEL
yaml_to_markdown-0.1.1744598339.dist-info/entry_points.txt
yaml_to_markdown-0.1.1744598339.dist-info/top_level.txt
yaml_to_markdown-0.1.1744598339.dist-info/RECORD
