Metadata-Version: 2.4
Name: yaml-to-markdown
Version: 0.1.1744598339
Summary: Converts a YAML/JSON file or python Dict/List to a Markdown file
Home-page: https://anevis.github.io/yaml-to-markdown/
Author: anevis
License: MIT
License-File: LICENSE
Requires-Dist: click==8.1.8
Requires-Dist: jsonschema[format]==4.23.0
Requires-Dist: pyyaml==6.0.2
Dynamic: author
Dynamic: description
Dynamic: description-content-type
Dynamic: home-page
Dynamic: license
Dynamic: license-file
Dynamic: requires-dist
Dynamic: summary
